modelmaker/__init__.py
modelmaker/estimator.py
modelmaker/model.py
modelmaker/predictor.py
modelmaker/session.py
modelmaker/client/__init__.py
modelmaker/client/api_client.py
modelmaker/client/configuration.py
modelmaker/client/rest.py
modelmaker/client/api/__init__.py
modelmaker/client/api/algorithm_api.py
modelmaker/client/api/framewrok_api.py
modelmaker/client/api/model_api.py
modelmaker/client/api/service_api.py
modelmaker/client/api/spec_api.py
modelmaker/client/api/train_job_api.py
modelmaker/config/__init__.py
modelmaker/config/auth.py
modelmaker/config/config.json
modelmaker/config/config.py
modelmaker/config/config_exception.py
modelmaker/exception/__init__.py
modelmaker/exception/iam_exception.py
modelmaker/exception/s3_exception.py
modelmaker/exception/train_exception.py
modelmaker/schema/__init__.py
modelmaker/schema/test.py
modelmaker/util/__init__.py
modelmaker/util/s3_util.py
modelmaker-2.0.1.data/scripts/mlcmd
modelmaker-2.0.1.dist-info/LICENSE
modelmaker-2.0.1.dist-info/METADATA
modelmaker-2.0.1.dist-info/WHEEL
modelmaker-2.0.1.dist-info/top_level.txt
modelmaker-2.0.1.dist-info/RECORD
