Metadata-Version: 2.1
Name: modelmaker
Version: 2.0.1
Summary: Wangsu ai sdk
Home-page: https://github.com/AiModelMaker/ModelMaker
Author: wangjm
Author-email: wangjm2@wangsu.com
License: MIT
Platform: UNKNOWN
Classifier: Development Status :: 4 - Beta
Classifier: Operating System :: OS Independent
Classifier: Intended Audience :: Developers
Classifier: License :: OSI Approved :: MIT License
Classifier: Programming Language :: Python :: Implementation
Classifier: Programming Language :: Python :: 3.6
Classifier: Topic :: Software Development :: Libraries
Requires-Python: >=3
Requires-Dist: requests (>=2.14.2)
Requires-Dist: urllib3 (<1.25,>=1.21.1)
Requires-Dist: boto3 (>=1.4.5)
Requires-Dist: botocore (>=1.5.92)
Requires-Dist: readline
